LICENSE
MANIFEST.in
README.md
setup.py
libpythonpro2/__init__.py
libpythonpro2/github_api.py
libpythonpro2/spam/__init__.py
libpythonpro2/spam/db.py
libpythonpro2/spam/enviador_de_email.py
libpythonpro2/spam/main.py
libpythonpro2/spam/modelos.py
libpythonpro2/tests/__init__.py
libpythonpro2/tests/test_exemplo.py
libpythonpro2/tests/test_spam/__init__.py
libpythonpro2/tests/test_spam/conftest.py
libpythonpro2/tests/test_spam/test_enviador_de_email.py
libpythonpro2/tests/test_spam/test_envio_para_base_de_usuarios.py
libpythonpro2/tests/test_spam/test_github_api.py
libpythonpro2/tests/test_spam/test_usuarios.py
libpythonpro_lmm.egg-info/PKG-INFO
libpythonpro_lmm.egg-info/SOURCES.txt
libpythonpro_lmm.egg-info/dependency_links.txt
libpythonpro_lmm.egg-info/not-zip-safe
libpythonpro_lmm.egg-info/requires.txt
libpythonpro_lmm.egg-info/top_level.txt